rasta/__init__.py
rasta/gpx.py
rasta/gtfs.py
rasta/keplergl_config.json
rasta/navigate_with_here.py
rasta/navigate_with_otp.py
rasta/process_geo_data.py
rasta/rasta_kepler.py
rasta-0.0.4.dist-info/AUTHORS.rst
rasta-0.0.4.dist-info/LICENSE
rasta-0.0.4.dist-info/METADATA
rasta-0.0.4.dist-info/WHEEL
rasta-0.0.4.dist-info/top_level.txt
rasta-0.0.4.dist-info/RECORD
