Metadata-Version: 2.1
Name: rasta
Version: 0.0.4
Summary: Description 
Home-page: https://github.com/ikespand/rasta
Author: Sandeep Pandey
Author-email: spandey.ike@gmail.com
License: MIT license
Keywords: rasta,geojson,gtfs,geospatial,keplergl
Platform: UNKNOWN
Classifier: License :: OSI Approved :: MIT License
Classifier: Natural Language :: English
Classifier: Programming Language :: Python :: 3
Requires-Python: >=3.6
License-File: LICENSE
License-File: AUTHORS.rst
Requires-Dist: click (==7.1.2)
Requires-Dist: gpxpy (>=1.4.1)
Requires-Dist: pandas (>=1.1.1)
Requires-Dist: geopandas (>=0.6.0)
Requires-Dist: shapely (>=1.6.4)
Requires-Dist: numpy (>=1.19.1)
Requires-Dist: requests (>=2.24.0)
Requires-Dist: polyline (==1.4.0)
Requires-Dist: nbconvert (==6.5.0)
Requires-Dist: keplergl (==0.2.0)
Requires-Dist: keplergl-cli
